darglint/__init__.py
darglint/analysis/__init__.py
darglint/analysis/analysis_visitor.py
darglint/analysis/argument_visitor.py
darglint/analysis/assert_visitor.py
darglint/analysis/function_and_method_visitor.py
darglint/analysis/function_scoped_visitor.py
darglint/analysis/raise_visitor.py
darglint/analysis/return_visitor.py
darglint/analysis/variable_visitor.py
darglint/analysis/yield_visitor.py
darglint/config.py
darglint/custom_assert.py
darglint/docstring/__init__.py
darglint/docstring/base.py
darglint/docstring/docstring.py
darglint/docstring/google.py
darglint/docstring/numpy.py
darglint/docstring/sections.py
darglint/docstring/sphinx.py
darglint/docstring/style.py
darglint/driver.py
darglint/error_report.py
darglint/errors.py
darglint/flake8_entry.py
darglint/function_description.py
darglint/integrity_checker.py
darglint/lex.py
darglint/node.py
darglint/parse/__init__.py
darglint/parse/combinator.py
darglint/parse/cyk.py
darglint/parse/google.py
darglint/parse/grammar.py
darglint/parse/grammars/Makefile
darglint/parse/grammars/__init__.py
darglint/parse/grammars/google_arguments_section.bnf
darglint/parse/grammars/google_arguments_section.py
darglint/parse/grammars/google_base.bnf
darglint/parse/grammars/google_long_description.bnf
darglint/parse/grammars/google_long_description.py
darglint/parse/grammars/google_raises_section.bnf
darglint/parse/grammars/google_raises_section.py
darglint/parse/grammars/google_returns_section.bnf
darglint/parse/grammars/google_returns_section.py
darglint/parse/grammars/google_returns_section_without_type.bnf
darglint/parse/grammars/google_returns_section_without_type.py
darglint/parse/grammars/google_short_description.bnf
darglint/parse/grammars/google_short_description.py
darglint/parse/grammars/google_types.bnf
darglint/parse/grammars/google_yields_section.bnf
darglint/parse/grammars/google_yields_section.py
darglint/parse/grammars/google_yields_section_without_type.bnf
darglint-1.6.0.dist-info/entry_points.txt
darglint-1.6.0.dist-info/LICENSE.txt
darglint-1.6.0.dist-info/WHEEL
darglint-1.6.0.dist-info/METADATA
darglint-1.6.0.dist-info/RECORD
